{"nodes":[{"id":"telegram_plan_session","label":"plan-session.ts","file_type":"code","source_file":"modes/telegram/plan-session.ts","source_location":"L1"},{"id":"telegram_plan_session_plansession","label":"PlanSession","file_type":"code","source_file":"modes/telegram/plan-session.ts","source_location":"L5"},{"id":"telegram_plan_session_plansessions","label":"planSessions","file_type":"code","source_file":"modes/telegram/plan-session.ts","source_location":"L10"},{"id":"telegram_plan_session_planmessage","label":"planMessage()","file_type":"code","source_file":"modes/telegram/plan-session.ts","source_location":"L12"},{"id":"telegram_plan_session_plankeyboard","label":"planKeyboard()","file_type":"code","source_file":"modes/telegram/plan-session.ts","source_location":"L27"},{"id":"telegram_plan_session_refreshplanui","label":"refreshPlanUi()","file_type":"code","source_file":"modes/telegram/plan-session.ts","source_location":"L43"}],"edges":[{"source":"telegram_plan_session","target":"telegraf","relation":"imports_from","confidence":"EXTRACTED","source_file":"modes/telegram/plan-session.ts","source_location":"L1","weight":1},{"source":"telegram_plan_session","target":"c_openarch_build_modes_plan_types_ts","relation":"imports_from","confidence":"EXTRACTED","source_file":"modes/telegram/plan-session.ts","source_location":"L2","weight":1},{"source":"telegram_plan_session","target":"plan_types_plan","relation":"imports","confidence":"EXTRACTED","source_file":"modes/telegram/plan-session.ts","source_location":"L2","weight":1},{"source":"telegram_plan_session","target":"telegram_plan_session_plansession","relation":"contains","confidence":"EXTRACTED","source_file":"modes/telegram/plan-session.ts","source_location":"L5","weight":1},{"source":"telegram_plan_session","target":"telegram_plan_session_plansessions","relation":"contains","confidence":"EXTRACTED","source_file":"modes/telegram/plan-session.ts","source_location":"L10","weight":1},{"source":"telegram_plan_session","target":"telegram_plan_session_planmessage","relation":"contains","confidence":"EXTRACTED","source_file":"modes/telegram/plan-session.ts","source_location":"L12","weight":1},{"source":"telegram_plan_session","target":"telegram_plan_session_plankeyboard","relation":"contains","confidence":"EXTRACTED","source_file":"modes/telegram/plan-session.ts","source_location":"L27","weight":1},{"source":"telegram_plan_session","target":"telegram_plan_session_refreshplanui","relation":"contains","confidence":"EXTRACTED","source_file":"modes/telegram/plan-session.ts","source_location":"L43","weight":1},{"source":"telegram_plan_session_refreshplanui","target":"telegram_plan_session_planmessage","relation":"calls","confidence":"EXTRACTED","source_file":"modes/telegram/plan-session.ts","source_location":"L47","weight":1},{"source":"telegram_plan_session_refreshplanui","target":"telegram_plan_session_plankeyboard","relation":"calls","confidence":"EXTRACTED","source_file":"modes/telegram/plan-session.ts","source_location":"L49","weight":1}]}